{
  "$schema": "https://developer.microsoft.com/json-schemas/spfx-build/package-solution.schema.json",
  "solution": {
    "name": "react-spfx-client-side-solution",
    "id": "8e789e89-ddcb-4359-ac41-a451191a4dd6",
    "version": "1.0.0.0",
    "includeClientSideAssets": true,
    "skipFeatureDeployment": true,
    "isDomainIsolated": false,
    "developer": {
      "name": "",
      "websiteUrl": "",
      "privacyUrl": "",
      "termsOfUseUrl": "",
      "mpnId": "Undefined-1.21.1"
    },
    "metadata": {
      "shortDescription": {
        "default": "react-spfx description"
      },
      "longDescription": {
        "default": "react-spfx description"
      },
      "screenshotPaths": [],
      "videoUrl": "",
      "categories": []
    },
    "features": [
      {
        "title": "react-spfx Feature",
        "description": "The feature that activates elements of the react-spfx solution.",
        "id": "1b84a3c8-abbf-4f85-9b14-7c0c8fbad24e",
        "version": "1.0.0.0"
      }
    ]
  },
  "paths": {
    "zippedPackage": "solution/react-spfx.sppkg"
  }
}
